getuser/__init__.py
getuser/__main__.py
getuser/error.py
getuser/get.py
getuser/py.typed
getuser/unix.py
getuser/userdata.py
getuser/win32.py
getuser-0.1.1.dist-info/METADATA
getuser-0.1.1.dist-info/WHEEL
getuser-0.1.1.dist-info/licenses/LICENSE
getuser-0.1.1.dist-info/RECORD
