Metadata-Version: 2.4
Name: getuser
Version: 0.1.1
Summary: Cross-platform user data retrieval utilities.
Project-URL: Homepage, https://github.com/ChenPi11/getuser
Author-email: ChenPi11 <wushengwuxi-msctinoulk@outlook.com>
License-File: LICENSE
Classifier: License :: OSI Approved :: The Unlicense (Unlicense)
Classifier: Operating System :: OS Independent
Classifier: Programming Language :: Python :: 3
Requires-Python: >=3.8
Requires-Dist: pywin32; sys_platform == 'win32'
Provides-Extra: dev
Requires-Dist: build; extra == 'dev'
Requires-Dist: ipython; extra == 'dev'
Requires-Dist: pylint; extra == 'dev'
Requires-Dist: pyright; extra == 'dev'
Requires-Dist: pytest; extra == 'dev'
Provides-Extra: ruff
Requires-Dist: ruff; extra == 'ruff'
